ytranslate/__init__.py
ytranslate/catalog.py
ytranslate/fsloader.py
ytranslate/loader.py
ytranslate/tools.py
ytranslate/commands/__init__.py
ytranslate/commands/base.py
ytranslate/commands/catalogs.py
ytranslate/commands/command.py
ytranslate/commands/main.py
ytranslate/commands/update.py
ytranslate/tests/__init__.py
ytranslate/tests/test_catalog.py
ytranslate/tests/test_fsloader.py
ytranslate-0.3.dist-info/LICENSE
ytranslate-0.3.dist-info/METADATA
ytranslate-0.3.dist-info/WHEEL
ytranslate-0.3.dist-info/entry_points.txt
ytranslate-0.3.dist-info/top_level.txt
ytranslate-0.3.dist-info/RECORD
