Metadata-Version: 2.1
Name: ytranslate
Version: 0.3
Summary: Ytranslate (Why translate) is a simple tool to manage translations
Requires-Dist: pyyaml (>=3)
